stackds/__init__.py
stackds/stack.py
stackds-0.1.0.dist-info/LICENSE
stackds-0.1.0.dist-info/METADATA
stackds-0.1.0.dist-info/WHEEL
stackds-0.1.0.dist-info/top_level.txt
stackds-0.1.0.dist-info/RECORD
